f_lib/__init__.py
f_lib/_environment.py
f_lib/_os_info.py
f_lib/_system_info.py
f_lib/archive_extractor/__init__.py
f_lib/archive_extractor/_archive_extractor.py
f_lib/archive_extractor/_tar_extractor.py
f_lib/archive_extractor/_zip_extractor.py
f_lib/archive_extractor/exceptions.py
f_lib/aws/__init__.py
f_lib/aws/aws_lambda/__init__.py
f_lib/aws/aws_lambda/type_defs.py
f_lib/constants.py
f_lib/logging/__init__.py
f_lib/logging/_console_handler.py
f_lib/logging/_constants.py
f_lib/logging/_extendable_highlighter.py
f_lib/logging/_fluid_log_render.py
f_lib/logging/_log_level.py
f_lib/logging/_logger.py
f_lib/logging/_prefix_adaptor.py
f_lib/logging/_setup_logging.py
f_lib/logging/settings/__init__.py
f_lib/logging/settings/_console_logging_settings.py
f_lib/logging/settings/_logging_settings.py
f_lib/logging/utils.py
f_lib/mixins/__init__.py
f_lib/mixins/_cli_interface.py
f_lib/mixins/_del_cached_prop.py
f_lib/py.typed
f_lib/utils/__init__.py
f_lib/utils/_file_hash.py
f_lib-0.4.3.dist-info/LICENSE
f_lib-0.4.3.dist-info/METADATA
f_lib-0.4.3.dist-info/WHEEL
f_lib-0.4.3.dist-info/RECORD
